PyConsoleMenu2/__init__.py
PyConsoleMenu2/base.py
PyConsoleMenu2/error.py
PyConsoleMenu2/menu.py
PyConsoleMenu2/utils.py
pyconsolemenu2-1.2.0.dist-info/METADATA
pyconsolemenu2-1.2.0.dist-info/WHEEL
pyconsolemenu2-1.2.0.dist-info/licenses/LICENSE.md
pyconsolemenu2-1.2.0.dist-info/RECORD
