Metadata-Version: 2.3
Name: PyConsoleMenu2
Version: 1.2.0
Summary: An extreamly easy to use Python console menu
Project-URL: Homepage, https://github.com/lxl66566/PyConsoleMenu2
Project-URL: Repository, https://github.com/lxl66566/PyConsoleMenu2.git
License-File: LICENSE.md
Keywords: console,menu
Classifier: License :: OSI Approved :: MIT License
Classifier: Programming Language :: Python :: 3
Classifier: Programming Language :: Python :: 3.7
Classifier: Programming Language :: Python :: 3.8
Classifier: Programming Language :: Python :: 3.9
Classifier: Programming Language :: Python :: 3.10
Classifier: Programming Language :: Python :: 3.11
Classifier: Programming Language :: Python :: 3.12
Requires-Python: >=3.7
Requires-Dist: windows-curses>=2.3.3; platform_system == 'Windows'
